blog/__init__.py
blog/apps.py
blog/factory.py
blog/filters.py
blog/models.py
blog/urls.py
blog/views.py
blog/management/__init__.py
blog/management/commands/__init__.py
blog/management/commands/populate_db.py
blog/migrations/0001_initial.py
blog/migrations/0002_alter_blog_options_blog_details.py
blog/migrations/0003_blog_image.py
blog/migrations/__init__.py
blog/static/blog/blog.js
blog/templates/_bulk_actions.html
blog/templates/blog/_actions.html
blog/templates/blog/_grid_item.html
blog/templates/blog/_header.html
blog/templates/blog/_list_item.html
blog/templates/blog/_modals.html
blog/templates/blog/_table_row.html
blog/templates/users/details/index.html
blog/templates/users/table/_table_row.html
dl/__init__.py
dl/asgi.py
dl/settings.py
dl/sidebars.py
dl/urls.py
dl/wsgi.py
dynamic_listing/__init__.py
dynamic_listing/app.py
dynamic_listing/apps.py
dynamic_listing/base.py
dynamic_listing/listing_factories.py
dynamic_listing/views.py
dynamic_listing/filters/__init__.py
dynamic_listing/filters/filter_field_renderer.py
dynamic_listing/filters/filter_renderer.py
dynamic_listing/filters/filters.py
dynamic_listing/locale/ar/LC_MESSAGES/django.mo
dynamic_listing/locale/ar/LC_MESSAGES/django.po
dynamic_listing/static/dynamic_listing/5-dark.png
dynamic_listing/static/dynamic_listing/5.png
dynamic_listing/static/dynamic_listing/dynamic_listing.js
dynamic_listing/templates/dynamic_listing/index.html
dynamic_listing/templates/dynamic_listing/filters/__as_list.html
dynamic_listing/templates/dynamic_listing/filters/__filters-footer.html
dynamic_listing/templates/dynamic_listing/filters/_side_filter.html
dynamic_listing/templates/dynamic_listing/filters/_top_filter.html
dynamic_listing/templates/dynamic_listing/filters/fields/checkbox.html
dynamic_listing/templates/dynamic_listing/filters/fields/checkbox_group.html
dynamic_listing/templates/dynamic_listing/filters/fields/date-range.html
dynamic_listing/templates/dynamic_listing/filters/fields/input.html
dynamic_listing-1.0.25.dist-info/LICENSE
dynamic_listing-1.0.25.dist-info/METADATA
dynamic_listing-1.0.25.dist-info/WHEEL
dynamic_listing-1.0.25.dist-info/top_level.txt
dynamic_listing-1.0.25.dist-info/RECORD
